buka
